xontrib/gruvbox.py
xontrib_gruvbox-0.1.3.dist-info/LICENSE
xontrib_gruvbox-0.1.3.dist-info/WHEEL
xontrib_gruvbox-0.1.3.dist-info/METADATA
xontrib_gruvbox-0.1.3.dist-info/RECORD
