Metadata-Version: 2.1
Name: xontrib-gruvbox
Version: 0.1.3
Summary: A Gruvbox theme for xonsh.
License: MIT
Author: Ryan Delaney
Author-email: ryan.patrick.delaney+pypi@protonmail.com
Requires-Python: >=3.6
Classifier: License :: OSI Approved :: MIT License
Classifier: Programming Language :: Python :: 3
Classifier: Programming Language :: Python :: 3.10
Classifier: Programming Language :: Python :: 3.6
Classifier: Programming Language :: Python :: 3.7
Classifier: Programming Language :: Python :: 3.8
Classifier: Programming Language :: Python :: 3.9
Requires-Dist: xonsh
